waas_client/__init__.py
waas_client/client.py
waas_client-0.0.2.dist-info/METADATA
waas_client-0.0.2.dist-info/WHEEL
waas_client-0.0.2.dist-info/top_level.txt
waas_client-0.0.2.dist-info/RECORD
